setup.py
bin/raccoon
raccoon/__init__.py
raccoon/raccoon.py
raccoontest.egg-info/PKG-INFO
raccoontest.egg-info/SOURCES.txt
raccoontest.egg-info/dependency_links.txt
raccoontest.egg-info/not-zip-safe
raccoontest.egg-info/top_level.txt