Metadata-Version: 1.0
Name: raccoontest
Version: 0.8
Summary: Raccoon is a language wrapper for SQL that makes it easier and more intuitive to write SQL code.
Home-page: https://github.com/jasondecastro/raccoon
Author: Jason Decastro
Author-email: jasonrdecastro@gmail.com
License: Copyright (c) 2016, Jason Decastro
